a_pandas_ex_multiloc/LICENSE
a_pandas_ex_multiloc/README.MD
a_pandas_ex_multiloc/__init__.py
a_pandas_ex_multiloc/requirements.txt
a_pandas_ex_multiloc/thirdparty.json
a_pandas_ex_multiloc-0.10.dist-info/LICENSE.rst
a_pandas_ex_multiloc-0.10.dist-info/METADATA
a_pandas_ex_multiloc-0.10.dist-info/WHEEL
a_pandas_ex_multiloc-0.10.dist-info/top_level.txt
a_pandas_ex_multiloc-0.10.dist-info/RECORD
